quantnet/__init__.py
quantnet/baselines.py
quantnet/utils.py
quantnet/no_transfer/__init__.py
quantnet/no_transfer/linear.py
quantnet/no_transfer/linear_linear.py
quantnet/no_transfer/linear_lstm.py
quantnet/no_transfer/lstm.py
quantnet/no_transfer/lstm_linear.py
quantnet/no_transfer/lstm_lstm.py
quantnet-0.1.0.dist-info/LICENSE.md
quantnet-0.1.0.dist-info/METADATA
quantnet-0.1.0.dist-info/WHEEL
quantnet-0.1.0.dist-info/top_level.txt
quantnet-0.1.0.dist-info/RECORD
