Metadata-Version: 2.1
Name: quantnet
Version: 0.1.0
Summary: A PyTorch implementation of QuantNet: Transferring Learning Across Systematic Trading Strategies.
Home-page: https://github.com/brilhana/quantnet
Author: Alexandre Brilhante
Author-email: alexandre.brilhante@gmail.com
Project-URL: Bug Tracker, https://github.com/brilhana/quantnet/issues
Classifier: Programming Language :: Python :: 3
Classifier: License :: OSI Approved :: MIT License
Classifier: Operating System :: OS Independent
Requires-Python: >=3.8
License-File: LICENSE.md
